MANIFEST.in
setup.py
_lzmaffi_mods/__init__.py
lzmaffi/__init__.py
lzmaffi/_lzmamodule2.py
lzmaffi/compat.py
lzmaffi.egg-info/PKG-INFO
lzmaffi.egg-info/SOURCES.txt
lzmaffi.egg-info/dependency_links.txt
lzmaffi.egg-info/not-zip-safe
lzmaffi.egg-info/requires.txt
lzmaffi.egg-info/top_level.txt
lzmaffi/__pycache__/_compiled_module.c
test/test_lzma.py