Metadata-Version: 1.0
Name: lzmaffi
Version: 0.3.0
Summary: Port of Python 3.3's 'lzma' module for XZ/LZMA compressed files to cffi.
Home-page: https://github.com/r3m0t/backports.lzma
Author: Tomer Chachamu, based on work by Peter Cock
Author-email: tomer.chachamu@gmail.com
License: 3-clause BSD License
Keywords: xz lzma compression decompression cffi ffi
Platform: UNKNOWN
Classifier: Development Status :: 5 - Production/Stable
Classifier: Programming Language :: Python
Classifier: Programming Language :: Python :: 2.7
Classifier: Programming Language :: Python :: 3
Classifier: Topic :: Software Development :: Libraries :: Python Modules
Classifier: Intended Audience :: Developers
Classifier: License :: OSI Approved :: BSD License
Classifier: Topic :: System :: Archiving :: Compression
